LICENSE
MANIFEST.in
setup.py
sysinfo/__init__.py
sysinfo/humansize.py
sysinfo/sysinfo.py
sysinfo.egg-info/PKG-INFO
sysinfo.egg-info/SOURCES.txt
sysinfo.egg-info/dependency_links.txt
sysinfo.egg-info/requires.txt
sysinfo.egg-info/top_level.txt